mythic_lite/__init__.py
mythic_lite/core/__init__.py
mythic_lite/core/chatbot_orchestrator.py
mythic_lite/core/config.py
mythic_lite/core/conversation_worker.py
mythic_lite/core/model_manager.py
mythic_lite/scripts/__init__.py
mythic_lite/scripts/download_vosk_manual.py
mythic_lite/scripts/initialize_models.py
mythic_lite/scripts/setup_environment.py
mythic_lite/utils/__init__.py
mythic_lite/utils/cli.py
mythic_lite/utils/logger.py
mythic_lite/utils/windows_input.py
mythic_lite/workers/__init__.py
mythic_lite/workers/asr_worker.py
mythic_lite/workers/llm_worker.py
mythic_lite/workers/memory_worker.py
mythic_lite/workers/tts_worker.py
mythic_lite-0.1.1.dist-info/METADATA
mythic_lite-0.1.1.dist-info/WHEEL
mythic_lite-0.1.1.dist-info/entry_points.txt
mythic_lite-0.1.1.dist-info/top_level.txt
mythic_lite-0.1.1.dist-info/RECORD
