Metadata-Version: 2.4
Name: mythic-lite
Version: 0.1.1
Summary: A lightweight, local AI chatbot system with text-to-speech capabilities
Author-email: Hoang Le <lhqezio1010@gmail.com>
Maintainer-email: Hoang Le <lhqezio1010@gmail.com>
License: MIT
Project-URL: Homepage, https://github.com/mythic-lite/mythic-lite
Project-URL: Documentation, https://mythic-lite.readthedocs.io
Project-URL: Repository, https://github.com/mythic-lite/mythic-lite.git
Project-URL: Bug Tracker, https://github.com/mythic-lite/mythic-lite/issues
Project-URL: Changelog, https://github.com/mythic-lite/mythic-lite/blob/main/CHANGELOG.md
Keywords: ai,chatbot,llm,tts,asr,local,privacy,offline
Classifier: Development Status :: 3 - Alpha
Classifier: Intended Audience :: Developers
Classifier: Intended Audience :: End Users/Desktop
Classifier: License :: OSI Approved :: MIT License
Classifier: Operating System :: OS Independent
Classifier: Programming Language :: Python :: 3
Classifier: Programming Language :: Python :: 3.8
Classifier: Programming Language :: Python :: 3.9
Classifier: Programming Language :: Python :: 3.10
Classifier: Programming Language :: Python :: 3.11
Classifier: Programming Language :: Python :: 3.12
Classifier: Topic :: Communications :: Chat
Classifier: Topic :: Scientific/Engineering :: Artificial Intelligence
Classifier: Topic :: Multimedia :: Sound/Audio :: Speech
Requires-Python: >=3.8
Requires-Dist: llama-cpp-python>=0.2.0
Requires-Dist: piper-tts>=1.2.0
Requires-Dist: numpy>=1.21.0
Requires-Dist: PyAudio>=0.2.11
Requires-Dist: colorama>=0.4.6
Requires-Dist: rich>=13.7.0
Requires-Dist: click>=8.1.7
Requires-Dist: python-dotenv>=1.0.0
Requires-Dist: typing-extensions>=4.8.0
Requires-Dist: huggingface-hub>=0.19.0
Requires-Dist: requests>=2.31.0
Requires-Dist: vosk>=0.3.44
Requires-Dist: windows-curses>=2.3.1; sys_platform == "win32"
Provides-Extra: dev
Requires-Dist: pytest>=7.0.0; extra == "dev"
Requires-Dist: pytest-cov>=4.0.0; extra == "dev"
Requires-Dist: black>=23.0.0; extra == "dev"
Requires-Dist: isort>=5.12.0; extra == "dev"
Requires-Dist: flake8>=6.0.0; extra == "dev"
Requires-Dist: mypy>=1.0.0; extra == "dev"
Provides-Extra: docs
Requires-Dist: sphinx>=6.0.0; extra == "docs"
Requires-Dist: sphinx-rtd-theme>=1.2.0; extra == "docs"
Requires-Dist: myst-parser>=1.0.0; extra == "docs"
